{"name":"Au3 db","body":"### Getting Started\r\nThis is my code:\r\n`\r\npublic class CarDealer {\r\n\tpublic String owner;\r\n\t\r\n\tpublic static void main( String[] args ){\r\n\t\tArrayList<Car> stock = new ArrayList<Car>();\r\n\t\tstock.add( new Car(\"Audi\", 180, \"blue\", new Driver(\"Johannes\", 21)) );\r\n\t\tstock.add( new Car(\"BMW\", 210, \"grey\", new Driver(\"Martin\", 33)) );\r\n\t\tstock.add( new Car(\"Mini\", 280, \"green\", new Driver(\"Jana\", 54)) );\r\n\t\tListIterator<Car> it = stock.listIterator( stock.size() );\r\n\t    while( it.hasPrevious() ){\r\n\t    \tSystem.out.println( it.previous().getName());\r\n\t    }\r\n\t}\r\n}`","tagline":"the biggest sh** ever dumped in this page","google":"","note":"Don't delete this file! It's used internally to help with page regeneration."}